togai_client/__init__.py
togai_client/api_client.py
togai_client/api_response.py
togai_client/configuration.py
togai_client/exceptions.py
togai_client/model_utils.py
togai_client/py.typed
togai_client/rest.py
togai_client/api/__init__.py
togai_client/api/accounts_api.py
togai_client/api/add_ons_api.py
togai_client/api/alerts_api.py
togai_client/api/aliases_api.py
togai_client/api/authentication_api.py
togai_client/api/credits_api.py
togai_client/api/customer_portal_api.py
togai_client/api/customers_api.py
togai_client/api/entitlements_api.py
togai_client/api/event_ingestion_api.py
togai_client/api/event_management_api.py
togai_client/api/event_schemas_api.py
togai_client/api/feature_api.py
togai_client/api/file_storage_api.py
togai_client/api/invoice_groups_api.py
togai_client/api/invoices_api.py
togai_client/api/jobs_api.py
togai_client/api/licenses_api.py
togai_client/api/metrics_api.py
togai_client/api/payments_api.py
togai_client/api/price_experimentation_api.py
togai_client/api/price_plan_v2_api.py
togai_client/api/price_plans_api.py
togai_client/api/pricing_rules_api.py
togai_client/api/reports_api.py
togai_client/api/schedules_api.py
togai_client/api/settings_api.py
togai_client/api/usage_meters_api.py
togai_client/api/wallet_api.py
togai_client/apis/__init__.py
togai_client/model/__init__.py
togai_client/model/account.py
togai_client/model/account_aliases.py
togai_client/model/account_paginated_response.py
togai_client/model/add_account_aliases_request.py
togai_client/model/associate_price_plan_request.py
togai_client/model/associate_price_plan_response.py
togai_client/model/base_success_response.py
togai_client/model/bundle.py
togai_client/model/computation.py
togai_client/model/create_account_request.py
togai_client/model/create_customer_request.py
togai_client/model/create_customer_response.py
togai_client/model/create_event_schema_request.py
togai_client/model/create_price_plan_request.py
togai_client/model/create_usage_meter_request.py
togai_client-1.0.3.dist-info/METADATA
togai_client-1.0.3.dist-info/WHEEL
togai_client-1.0.3.dist-info/top_level.txt
togai_client-1.0.3.dist-info/RECORD
