Metadata-Version: 2.1
Name: togai-client
Version: 1.0.3
Summary: Togai Apis
Home-page: https://github.com/zuora/togai-python-client
Author: Togai Engineering
Author-email: engg@togai.com
License: Apache 2.0
Keywords: OpenAPI,OpenAPI-Generator,Togai Apis
Requires-Dist: urllib3>=1.25.3
Requires-Dist: python-dateutil
Requires-Dist: pydantic>=2
